torchtricks/callbacks.py
torchtricks/criterion.py
torchtricks/datasets.py
torchtricks/glove_utils.py
torchtricks/metrics.py
torchtricks/models.py
torchtricks/trainers.py
torchtricks/utils.py
torchtricks/vectorizers.py
torchtricks-0.0.2.dist-info/DESCRIPTION.rst
torchtricks-0.0.2.dist-info/METADATA
torchtricks-0.0.2.dist-info/RECORD
torchtricks-0.0.2.dist-info/WHEEL
torchtricks-0.0.2.dist-info/metadata.json
torchtricks-0.0.2.dist-info/top_level.txt
