Metadata-Version: 2.0
Name: torchtricks
Version: 0.0.2
Summary: PyTorch trainers, datasets, criterion, and utility functions
Home-page: https://github.com/A-Jacobson/TorchTricks
Author: UNKNOWN
Author-email: UNKNOWN
License: MIT
Download-URL: https://github.com/A-Jacobson/TorchTricks/archive/0.0.1.tar.gz
Platform: UNKNOWN
Classifier: Development Status :: 3 - Alpha
Classifier: Programming Language :: Python :: 3.6
Requires-Python: >=3
